pluckit/__init__.py
pluckit/native.py
pluckit/pluck.py
pluckit/pluckable.py
pluckit/pluckit.py
pluckit-0.6.0.dist-info/LICENSE.txt
pluckit-0.6.0.dist-info/METADATA
pluckit-0.6.0.dist-info/WHEEL
pluckit-0.6.0.dist-info/top_level.txt
pluckit-0.6.0.dist-info/RECORD
