Metadata-Version: 2.1
Name: pluckit
Version: 0.6.0
Summary: extract values from collection items
Home-page: https://github.com/dpep/py_pluckit
Author: Daniel Pepper
License: MIT
Platform: any
Classifier: License :: OSI Approved :: MIT License
Classifier: Programming Language :: Python
Classifier: Topic :: Utilities
